[
    {
        "year": 2011,
        "value": 14170,
        "name": "Arizona"
    },
    {
        "year": 2012,
        "value": 14211,
        "name": "Arizona"
    },
    {
        "year": 2013,
        "value": 12291,
        "name": "Arizona"
    },
    {
        "year": 2014,
        "value": 12709,
        "name": "Arizona"
    },
    {
        "year": 2015,
        "value": 12077,
        "name": "Arizona"
    },
    {
        "year": 2016,
        "value": 12863,
        "name": "Arizona"
    },
    {
        "year": 2017,
        "value": 13593,
        "name": "Arizona"
    },
    {
        "year": 2018,
        "value": 11090,
        "name": "Arizona"
    },
    {
        "year": 2019,
        "value": 11259,
        "name": "Arizona"
    },
    {
        "year": 2020,
        "value": 8728,
        "name": "Arizona"
    }
]