[
    {
        "name": "The United States",
        "income": "59640",
        "police_total": 18045.0
    },
    {
        "name": "Alabama",
        "income": "52667",
        "police_total": 14173
    },
    {
        "name": "Alaska",
        "income": "80661",
        "police_total": 1937
    },
    {
        "name": "Arizona",
        "income": "58556",
        "police_total": 21192
    },
    {
        "name": "Arkansas",
        "income": "43825",
        "police_total": 9250
    },
    {
        "name": "California",
        "income": "67663",
        "police_total": 117322
    },
    {
        "name": "Colorado",
        "income": "75586",
        "police_total": 17441
    },
    {
        "name": "Connecticut",
        "income": "77120",
        "police_total": 10349
    },
    {
        "name": "Delaware",
        "income": "60203",
        "police_total": 3168
    },
    {
        "name": "District of Columbia",
        "income": "66843",
        "police_total": 5065
    },
    {
        "name": "Florida",
        "income": "54016",
        "police_total": 67919
    },
    {
        "name": "Georgia",
        "income": "52302",
        "police_total": 29070
    },
    {
        "name": "Hawaii",
        "income": "71493",
        "police_total": 3658
    },
    {
        "name": "Idaho",
        "income": "53943",
        "police_total": 4272
    },
    {
        "name": "Illinois",
        "income": "60031",
        "police_total": 14563
    },
    {
        "name": "Indiana",
        "income": "55043",
        "police_total": 9703
    },
    {
        "name": "Iowa",
        "income": "66953",
        "police_total": 7747
    },
    {
        "name": "Kansas",
        "income": "53223",
        "police_total": 9249
    },
    {
        "name": "Kentucky",
        "income": "49950",
        "police_total": 9120
    },
    {
        "name": "Louisiana",
        "income": "51671",
        "police_total": 10987
    },
    {
        "name": "Maine",
        "income": "61167",
        "police_total": 2806
    },
    {
        "name": "Maryland",
        "income": "77189",
        "police_total": 22726
    },
    {
        "name": "Massachusetts",
        "income": "69594",
        "police_total": 19651
    },
    {
        "name": "Michigan",
        "income": "62959",
        "police_total": 22669
    },
    {
        "name": "Minnesota",
        "income": "71592",
        "police_total": 13348
    },
    {
        "name": "Mississippi",
        "income": "35992",
        "police_total": 4629
    },
    {
        "name": "Missouri",
        "income": "51535",
        "police_total": 20093
    },
    {
        "name": "Montana",
        "income": "48082",
        "police_total": 2542
    },
    {
        "name": "Nebraska",
        "income": "64134",
        "police_total": 4915
    },
    {
        "name": "Nevada",
        "income": "57704",
        "police_total": 8812
    },
    {
        "name": "New Hampshire",
        "income": "76907",
        "police_total": 3432
    },
    {
        "name": "New Jersey",
        "income": "70958",
        "police_total": 31952
    },
    {
        "name": "New Mexico",
        "income": "44704",
        "police_total": 776
    },
    {
        "name": "New York",
        "income": "55612",
        "police_total": 80143
    },
    {
        "name": "North Carolina",
        "income": "51573",
        "police_total": 33505
    },
    {
        "name": "North Dakota",
        "income": "65836",
        "police_total": 1992
    },
    {
        "name": "Ohio",
        "income": "56482",
        "police_total": 16934
    },
    {
        "name": "Oklahoma",
        "income": "51378",
        "police_total": 12216
    },
    {
        "name": "Oregon",
        "income": "54536",
        "police_total": 9787
    },
    {
        "name": "Pennsylvania",
        "income": "61388",
        "police_total": 30094
    },
    {
        "name": "Rhode Island",
        "income": "62687",
        "police_total": 3056
    },
    {
        "name": "South Carolina",
        "income": "48485",
        "police_total": 15050
    },
    {
        "name": "South Dakota",
        "income": "59448",
        "police_total": 2652
    },
    {
        "name": "Tennessee",
        "income": "48260",
        "police_total": 26564
    },
    {
        "name": "Texas",
        "income": "57215",
        "police_total": 78457
    },
    {
        "name": "Utah",
        "income": "67945",
        "police_total": 4776
    },
    {
        "name": "Vermont",
        "income": "72915",
        "police_total": 1575
    },
    {
        "name": "Virginia",
        "income": "73354",
        "police_total": 23766
    },
    {
        "name": "Washington",
        "income": "71145",
        "police_total": 14475
    },
    {
        "name": "West Virginia",
        "income": "47935",
        "police_total": 4496
    },
    {
        "name": "Wisconsin",
        "income": "57571",
        "police_total": 17989
    },
    {
        "name": "Wyoming",
        "income": "75061",
        "police_total": 2291
    }
]