{
    "results": [
        {
            "data_year": 2011,
            "civilian_ct": 4048,
            "female_civilian_ct": 2602,
            "female_officer_ct": 990,
            "female_total_ct": 3592,
            "male_civilian_ct": 1446,
            "male_officer_ct": 9279,
            "male_total_ct": 10725,
            "population": 6815859,
            "total_pe_ct": 14317,
            "state_id": 53,
            "state_name": "Washington",
            "state_abbr": "WA",
            "agency_count_pe_submitting": 255,
            "csv_header": null,
            "pe_ct_per_1000": 2.1
        },
        {
            "data_year": 2012,
            "civilian_ct": 4084,
            "female_civilian_ct": 2536,
            "female_officer_ct": 936,
            "female_total_ct": 3472,
            "male_civilian_ct": 1548,
            "male_officer_ct": 9192,
            "male_total_ct": 10740,
            "population": 6880100,
            "total_pe_ct": 14212,
            "state_id": 53,
            "state_name": "Washington",
            "state_abbr": "WA",
            "agency_count_pe_submitting": 253,
            "csv_header": null,
            "pe_ct_per_1000": 2.07
        },
        {
            "data_year": 2013,
            "civilian_ct": 4244,
            "female_civilian_ct": 2648,
            "female_officer_ct": 959,
            "female_total_ct": 3607,
            "male_civilian_ct": 1596,
            "male_officer_ct": 9272,
            "male_total_ct": 10868,
            "population": 6954564,
            "total_pe_ct": 14475,
            "state_id": 53,
            "state_name": "Washington",
            "state_abbr": "WA",
            "agency_count_pe_submitting": 251,
            "csv_header": null,
            "pe_ct_per_1000": 2.08
        },
        {
            "data_year": 2014,
            "civilian_ct": 4255,
            "female_civilian_ct": 2645,
            "female_officer_ct": 977,
            "female_total_ct": 3622,
            "male_civilian_ct": 1610,
            "male_officer_ct": 9334,
            "male_total_ct": 10944,
            "population": 7037348,
            "total_pe_ct": 14566,
            "state_id": 53,
            "state_name": "Washington",
            "state_abbr": "WA",
            "agency_count_pe_submitting": 249,
            "csv_header": null,
            "pe_ct_per_1000": 2.07
        },
        {
            "data_year": 2015,
            "civilian_ct": 4259,
            "female_civilian_ct": 2637,
            "female_officer_ct": 980,
            "female_total_ct": 3617,
            "male_civilian_ct": 1622,
            "male_officer_ct": 9371,
            "male_total_ct": 10993,
            "population": 7163761,
            "total_pe_ct": 14610,
            "state_id": 53,
            "state_name": "Washington",
            "state_abbr": "WA",
            "agency_count_pe_submitting": 258,
            "csv_header": null,
            "pe_ct_per_1000": 2.04
        },
        {
            "data_year": 2016,
            "civilian_ct": 4506,
            "female_civilian_ct": 2762,
            "female_officer_ct": 1013,
            "female_total_ct": 3775,
            "male_civilian_ct": 1744,
            "male_officer_ct": 9494,
            "male_total_ct": 11238,
            "population": 7258544,
            "total_pe_ct": 15013,
            "state_id": 53,
            "state_name": "Washington",
            "state_abbr": "WA",
            "agency_count_pe_submitting": 245,
            "csv_header": null,
            "pe_ct_per_1000": 2.07
        },
        {
            "data_year": 2017,
            "civilian_ct": 4667,
            "female_civilian_ct": 2878,
            "female_officer_ct": 1054,
            "female_total_ct": 3932,
            "male_civilian_ct": 1789,
            "male_officer_ct": 9662,
            "male_total_ct": 11451,
            "population": 7377379,
            "total_pe_ct": 15383,
            "state_id": 53,
            "state_name": "Washington",
            "state_abbr": "WA",
            "agency_count_pe_submitting": 234,
            "csv_header": null,
            "pe_ct_per_1000": 2.09
        },
        {
            "data_year": 2018,
            "civilian_ct": 5053,
            "female_civilian_ct": 2982,
            "female_officer_ct": 1066,
            "female_total_ct": 4048,
            "male_civilian_ct": 2071,
            "male_officer_ct": 9754,
            "male_total_ct": 11825,
            "population": 7535591,
            "total_pe_ct": 15873,
            "state_id": 53,
            "state_name": "Washington",
            "state_abbr": "WA",
            "agency_count_pe_submitting": 249,
            "csv_header": null,
            "pe_ct_per_1000": 2.11
        },
        {
            "data_year": 2019,
            "civilian_ct": 4975,
            "female_civilian_ct": 2987,
            "female_officer_ct": 1119,
            "female_total_ct": 4106,
            "male_civilian_ct": 1988,
            "male_officer_ct": 9910,
            "male_total_ct": 11898,
            "population": 7614893,
            "total_pe_ct": 16004,
            "state_id": 53,
            "state_name": "Washington",
            "state_abbr": "WA",
            "agency_count_pe_submitting": 250,
            "csv_header": null,
            "pe_ct_per_1000": 2.1
        },
        {
            "data_year": 2020,
            "civilian_ct": 4974,
            "female_civilian_ct": 2969,
            "female_officer_ct": 1153,
            "female_total_ct": 4122,
            "male_civilian_ct": 2005,
            "male_officer_ct": 9820,
            "male_total_ct": 11825,
            "population": 7693612,
            "total_pe_ct": 15947,
            "state_id": 53,
            "state_name": "Washington",
            "state_abbr": "WA",
            "agency_count_pe_submitting": 254,
            "csv_header": null,
            "pe_ct_per_1000": 2.07
        }
    ],
    "pagination": {
        "count": 10,
        "page": 0,
        "pages": 1,
        "per_page": 0
    }
}